grbl_link/__init__.py
grbl_link/cli.py
grbl_link/grbl_link.py
grbl_link/interface.py
grbl_link/messages.py
grbl_link/parser.py
grbl_link/protocol.py
grbl_link-0.1.4.dist-info/AUTHORS.rst
grbl_link-0.1.4.dist-info/LICENSE
grbl_link-0.1.4.dist-info/METADATA
grbl_link-0.1.4.dist-info/WHEEL
grbl_link-0.1.4.dist-info/entry_points.txt
grbl_link-0.1.4.dist-info/top_level.txt
grbl_link-0.1.4.dist-info/RECORD
