Metadata-Version: 2.1
Name: grbl-link
Version: 0.1.4
Summary: Interact seamlessly with a Grbl CNC controller. Stream files, jog, and receive status messages from a connected Grbl device.
Home-page: https://github.com/DariusMontez/grbl_link
Author: Darius Montez
Author-email: darius.montez@gmail.com
License: MIT license
Keywords: grbl_link
Platform: UNKNOWN
Classifier: Development Status :: 2 - Pre-Alpha
Classifier: Intended Audience :: Developers
Classifier: License :: OSI Approved :: MIT License
Classifier: Natural Language :: English
Classifier: Programming Language :: Python :: 2
Classifier: Programming Language :: Python :: 2.7
Classifier: Programming Language :: Python :: 3
Classifier: Programming Language :: Python :: 3.4
Classifier: Programming Language :: Python :: 3.5
Classifier: Programming Language :: Python :: 3.6
Requires-Dist: Click (>=6.0)
